AUTHORS.rst
LICENSE-Apache-2.0
LICENSE-LGPL-3.0
NOTICE
setup.cfg
setup.py
src/si_sr_gan_io/__init__.py
src/si_sr_gan_io/ecostress.py
src/si_sr_gan_io/ecostress_v2.py
src/si_sr_gan_io/hls.py
src/si_sr_gan_io/irregulargrid.py
src/si_sr_gan_io/landsat.py
src/si_sr_gan_io/master.py
src/si_sr_gan_io/mgrs.py
src/si_sr_gan_io/py.typed
src/si_sr_gan_io/regulargrid.py
src/si_sr_gan_io/sentinel2.py
src/si_sr_gan_io/sentinel2_l1c.py
src/si_sr_gan_io/srtm.py
src/si_sr_gan_io/storage.py
src/si_sr_gan_io/utils.py
src/si_sr_gan_io/venus.py
src/si_sr_gan_io/worldclim.py
src/si_sr_gan_io.egg-info/PKG-INFO
src/si_sr_gan_io.egg-info/SOURCES.txt
src/si_sr_gan_io.egg-info/dependency_links.txt
src/si_sr_gan_io.egg-info/not-zip-safe
src/si_sr_gan_io.egg-info/requires.txt
src/si_sr_gan_io.egg-info/top_level.txt
src/si_sr_gan_io/data/sentinel2/mgrs_tiles.gpkg
src/si_sr_gan_io/data/sentinel2/mgrs_tiles.gpkg.zip
src/si_sr_gan_io/data/sentinel2/orbits.gpkg
src/si_sr_gan_io/data/sentinel2/srs_sentinel2a.csv
src/si_sr_gan_io/data/sentinel2/srs_sentinel2b.csv
src/si_sr_gan_io/data/sentinel2/theia_s2.gpkg
src/si_sr_gan_io/data/venus/srs_venus.csv
src/si_sr_gan_io/data/venus/srs_venus.txt
src/si_sr_gan_io/data/venus/theia_venus.gpkg
tests/test_dem.py
tests/test_ecostress.py
tests/test_ecostress_v2.py
tests/test_hls.py
tests/test_irregulargrid.py
tests/test_landsat.py
tests/test_master.py
tests/test_mgrs.py
tests/test_regulargrid.py
tests/test_sentinel2.py
tests/test_sentinel2_l1c.py
tests/test_utils.py
tests/test_venus.py
tests/test_worldclim.py